odoo/addons/mrp_bom_matrix_report/README.rst
odoo/addons/mrp_bom_matrix_report/__init__.py
odoo/addons/mrp_bom_matrix_report/__manifest__.py
odoo/addons/mrp_bom_matrix_report/i18n/fr.po
odoo/addons/mrp_bom_matrix_report/i18n/it.po
odoo/addons/mrp_bom_matrix_report/i18n/mrp_bom_matrix_report.pot
odoo/addons/mrp_bom_matrix_report/readme/CONTRIBUTORS.md
odoo/addons/mrp_bom_matrix_report/readme/DESCRIPTION.md
odoo/addons/mrp_bom_matrix_report/readme/USAGE.md
odoo/addons/mrp_bom_matrix_report/reports/__init__.py
odoo/addons/mrp_bom_matrix_report/reports/mrp_bom_matrix_report.py
odoo/addons/mrp_bom_matrix_report/reports/mrp_bom_matrix_report_views.xml
odoo/addons/mrp_bom_matrix_report/security/ir.model.access.csv
odoo/addons/mrp_bom_matrix_report/static/description/icon.png
odoo/addons/mrp_bom_matrix_report/static/description/index.html
odoo_addon_mrp_bom_matrix_report-18.0.1.0.0.2.dist-info/METADATA
odoo_addon_mrp_bom_matrix_report-18.0.1.0.0.2.dist-info/WHEEL
odoo_addon_mrp_bom_matrix_report-18.0.1.0.0.2.dist-info/top_level.txt
odoo_addon_mrp_bom_matrix_report-18.0.1.0.0.2.dist-info/RECORD
